<annotation>
	<folder>bags_resized</folder>
	<filename>14.jpg</filename>
	<path>E:\VJ.Android\bags_resized\14.jpg</path>
	<source>
		<database>Unknown</database>
	</source>
	<size>
		<width>800</width>
		<height>600</height>
		<depth>3</depth>
	</size>
	<segmented>0</segmented>
	<object>
		<name>Bag</name>
		<pose>Unspecified</pose>
		<truncated>0</truncated>
		<difficult>0</difficult>
		<bndbox>
			<xmin>131</xmin>
			<ymin>170</ymin>
			<xmax>440</xmax>
			<ymax>399</ymax>
		</bndbox>
	</object>
</annotation>
